.gitignore
.travis.yml
LICENSE
README.md
README.pypi.rst
dev-requirements.txt
requirements.txt
run_tests_dev.py
setup.py
ga4gh/__init__.py
ga4gh/common/__init__.py
ga4gh/common/_version.py
ga4gh/common/cli.py
ga4gh/common/run_tests.py
ga4gh/common/utils.py
ga4gh_common.egg-info/PKG-INFO
ga4gh_common.egg-info/SOURCES.txt
ga4gh_common.egg-info/dependency_links.txt
ga4gh_common.egg-info/entry_points.txt
ga4gh_common.egg-info/namespace_packages.txt
ga4gh_common.egg-info/requires.txt
ga4gh_common.egg-info/top_level.txt
ga4gh_common.egg-info/zip-safe
tests/test_cli.py
tests/test_utils.py