Metadata-Version: 1.1
Name: ga4gh-common
Version: 0.0.5
Summary: Common utilities for GA4GH packages
Home-page: https://github.com/ga4gh/ga4gh-common
Author: Global Alliance for Genomics and Health
Author-email: theglobalalliance@genomicsandhealth.org
License: Apache License 2.0
Keywords: genomics,reference
Platform: UNKNOWN
Classifier: Development Status :: 3 - Alpha
Classifier: Intended Audience :: Science/Research
Classifier: License :: OSI Approved :: Apache Software License
Classifier: Natural Language :: English
Classifier: Programming Language :: Python :: 2.7
Classifier: Topic :: Scientific/Engineering :: Bio-Informatics
